{
  "category": "miscellaneous",
  "created_date": "2025-09-15T22:48:58.347779",
  "default_ports": [
    80,
    443,
    4222,
    8222
  ],
  "dependencies": [],
  "description": "nats is a free and open-source cloud native messaging system. NATS provides publish-subscribe, request-reply, and queue groups with at-most-once delivery, serving as a lightweight alternative to RabbitMQ or Kafka",
  "difficulty_level": "intermediate",
  "documentation_url": "https://howtomgr.github.io/miscellaneous/nats-server",
  "estimated_setup_time": "15-30 minutes",
  "features": [
    "multi-os-support",
    "comprehensive-documentation",
    "security-hardening",
    "performance-optimization",
    "backup-restore-procedures",
    "troubleshooting-guides"
  ],
  "guide_path": "/miscellaneous/nats-server",
  "installation_methods": [
    "native-packages",
    "source-compilation"
  ],
  "last_updated": "2025-09-15T22:48:58.347801",
  "license": "Open Source",
  "maintenance_status": "active",
  "name": "nats-server",
  "repository_url": "https://github.com/howtomgr/nats-server",
  "spec_version": "2.0",
  "subcategory": "miscellaneous",
  "supported_os": [
    "rhel",
    "centos",
    "rocky",
    "almalinux",
    "debian",
    "ubuntu",
    "arch",
    "alpine",
    "opensuse",
    "sles",
    "macos",
    "freebsd",
    "windows"
  ],
  "tags": [
    "miscellaneous",
    "containerization",
    "observability",
    "data-storage",
    "networking",
    "security",
    "data-protection"
  ],
  "title": "nats Installation Guide",
  "version": "1.0.0",
  "website_url": "https://howtomgr.github.io/miscellaneous/nats-server"
}